comodash_api_client_lowlevel/__init__.py
comodash_api_client_lowlevel/api_client.py
comodash_api_client_lowlevel/api_response.py
comodash_api_client_lowlevel/configuration.py
comodash_api_client_lowlevel/exceptions.py
comodash_api_client_lowlevel/rest.py
comodash_api_client_lowlevel/api/__init__.py
comodash_api_client_lowlevel/api/loads_api.py
comodash_api_client_lowlevel/api/migrations_api.py
comodash_api_client_lowlevel/api/queries_api.py
comodash_api_client_lowlevel/models/__init__.py
comodash_api_client_lowlevel/models/commit_load200_response.py
comodash_api_client_lowlevel/models/commit_load202_response.py
comodash_api_client_lowlevel/models/error.py
comodash_api_client_lowlevel/models/file_upload_request.py
comodash_api_client_lowlevel/models/file_upload_response.py
comodash_api_client_lowlevel/models/load.py
comodash_api_client_lowlevel/models/load_commit.py
comodash_api_client_lowlevel/models/load_commit_check_sum_value.py
comodash_api_client_lowlevel/models/load_id.py
comodash_api_client_lowlevel/models/load_meta_data.py
comodash_api_client_lowlevel/models/load_meta_data_error_messages_inner.py
comodash_api_client_lowlevel/models/migration.py
comodash_api_client_lowlevel/models/migration_status.py
comodash_api_client_lowlevel/models/query.py
comodash_api_client_lowlevel/models/query_id.py
comodash_api_client_lowlevel/models/query_result.py
comodash_api_client_lowlevel/models/query_result_result_set.py
comodash_api_client_lowlevel/models/query_result_result_set_meta_data.py
comodash_api_client_lowlevel/models/query_result_result_set_meta_data_column_info_inner.py
comodash_api_client_lowlevel/models/query_result_result_set_rows_inner.py
comodash_api_client_lowlevel/models/query_result_result_set_rows_inner_data_inner.py
comodash_api_client_lowlevel/models/query_status.py
comodash_api_client_lowlevel/models/query_text.py
comodash_api_client_lowlevel/test/__init__.py
comodash_api_client_lowlevel/test/test_commit_load200_response.py
comotion_sdk-1.1.1.dist-info/licenses/LICENSE
comotion_sdk-1.1.1.dist-info/METADATA
comotion_sdk-1.1.1.dist-info/WHEEL
comotion_sdk-1.1.1.dist-info/entry_points.txt
comotion_sdk-1.1.1.dist-info/top_level.txt
comotion_sdk-1.1.1.dist-info/RECORD
