Metadata-Version: 2.4
Name: comotion-sdk
Version: 1.1.1
Summary: SDK for interacting with the Comotion APIs
Home-page: https://github.com/ComotionLabs/comotion-sdk
Author: Comotion
Author-email: tim@comotion.us
Project-URL: Bug Tracker, https://github.com/ComotionLabs/comotion-sdk/issues
Classifier: Programming Language :: Python :: 3
Classifier: License :: OSI Approved :: Apache Software License
Classifier: Operating System :: OS Independent
Requires-Python: >=3.9
License-File: LICENSE
Requires-Dist: requests
Requires-Dist: pandas
Requires-Dist: click
Requires-Dist: keyring
Requires-Dist: pyjwt
Requires-Dist: urllib3
Requires-Dist: sqlalchemy
Requires-Dist: tqdm
Requires-Dist: aiohttp
Requires-Dist: pydantic
Requires-Dist: awswrangler
Dynamic: author
Dynamic: author-email
Dynamic: classifier
Dynamic: description
Dynamic: description-content-type
Dynamic: home-page
Dynamic: license-file
Dynamic: project-url
Dynamic: requires-dist
Dynamic: requires-python
Dynamic: summary
